emotigrad/__init__.py
emotigrad/base.py
emotigrad/colors.py
emotigrad/personalities.py
emotigrad/types.py
emotigrad-0.0.2.dist-info/licenses/LICENSE
emotigrad-0.0.2.dist-info/METADATA
emotigrad-0.0.2.dist-info/WHEEL
emotigrad-0.0.2.dist-info/top_level.txt
emotigrad-0.0.2.dist-info/RECORD
