Metadata-Version: 2.4
Name: emotigrad
Version: 0.0.2
Summary: Emotional optimizer wrappers for PyTorch training loops.
Author: Jordan Sinclair
License: MIT
Keywords: pytorch,optimizer,deep-learning,training,fun
Classifier: Programming Language :: Python :: 3
Classifier: License :: OSI Approved :: MIT License
Classifier: Intended Audience :: Developers
Classifier: Intended Audience :: Science/Research
Classifier: Topic :: Scientific/Engineering :: Artificial Intelligence
Requires-Python: >=3.9
License-File: LICENSE
Requires-Dist: torch
Requires-Dist: numpy
Provides-Extra: dev
Requires-Dist: pytest; extra == "dev"
Requires-Dist: black; extra == "dev"
Requires-Dist: ruff; extra == "dev"
Dynamic: license-file
